Workbook

Sheet Dashboard
A1: SYAMA GOLD | SAG PEBBLE (SCAT) SORTING | BUSINESS CASE
A2: Project: | B2: Syama Sulphide Conversion Project - converted (ex-oxide) SAG line
A3: Basis: | B3: STEINERT model SR241558 (Sukari) re-parameterised for Syama
A4: Date: | B4: 2026-08-05
B6: INPUTS | I6: OUTPUTS
B7: Parameter | C7: Value | D7: Unit | F7: Basis / source | G7: Confidence | I7: Parameter | J7: BASE | K7: SORTING | L7: DIFF | M7: Unit | N7: Comment
A9: OPERATION | I9: ROM feed rate | J9: =C10 | K9: ='MB Sort'!G5 | L9: =K9-J9 | M9: t/h | N9: uplift from rejecting scat mass
B10: New feed to SAG line | C10: 200 | D10: t/h | F10: 1.58 Mtpa - the SSCP increment (2.4 -> 4.0 Mtpa) | G10: Assumption - CONFIRM | I10: ROM grade | J10: ='MB Base'!H5 | K10: ='MB Sort'!H5 | L10: =K10-J10 | M10: g/t
B11: Annual operating hours | C11: 7884 | D11: h/a | F11: 90% availability | G11: Assumption | I11: SAG mill total load | J11: ='MB Base'!G99 | K11: ='MB Sort'!G99 | L11: =K11-J11 | M11: t/h | N11: new feed + circulating scats
B12: ROM grade (diluted) | C12: 2.4 | D12: g/t | F12: 2026 UG plan 2.4-2.5 g/t Au | G12: Resolute guidance | I12: Scat / sorter feed | J12: ='MB Base'!G106 | K12: ='MB Sort'!G106 | L12: =K12-J12 | M12: t/h
B13: Gold recovery (flot+roast+CIL) | C13: 0.75 | D13: - | F13: FY25 sulphide 75%, Q2-25 76% | G13: Resolute actual | I13: Scat grade | J13: ='MB Base'!H106 | K13: ='MB Sort'!H106 | L13: =K13-J13 | M13: g/t | N13: measured = 2.00 g/t
B14: Gold price | C14: 4000 | D14: $/oz | F14: Resolute 2026 planning assumption | G14: Resolute | I14: Sorter rejects | J14: ='MB Base'!G107 | K14: ='MB Sort'!G107 | L14: =K14-J14 | M14: t/h | N14: to waste dump
B15: Gold price | C15: =C14/31.1035 | D15: $/g | F15: gold price / 31.1035 | G15: Calculated | I15: Reject grade | J15: ='MB Base'!H107 | K15: ='MB Sort'!H107 | L15: =K15-J15 | M15: g/t | N15: gold discarded
B16: Discount rate | C16: 0.1 | D16: - | F16: 8% base + Mali country-risk premium | G16: Assumption | I16: Mass pull to rejects | J16: =IFERROR('MB Base'!G107/'MB Base'!G106,0) | K16: =IFERROR('MB Sort'!G107/'MB Sort'!G106,0) | L16: =K16-J16 | M16: - | N16: of the scat stream
A17: COSTS | I17: Ball-mill / leach feed | J17: ='MB Base'!G104 | K17: ='MB Sort'!G104 | L17: =K17-J17 | M17: t/h | N17: HELD CONSTANT (Goal Seek)
B18: Milling cost avoided | C18: 8 | D18: $/t | F18: power + media + reagents (Sukari used 7.69) | G18: Assumption - CONFIRM | I18: Leach feed grade | J18: ='MB Base'!H104 | K18: ='MB Sort'!H104 | L18: =K18-J18 | M18: g/t | N18: the uplift
B19: Incremental UG mining cost | C19: 53 | D19: $/t | F19: ~45% of AISC $2,050/oz at 1.8 g/t recovered | G19: Derived - CONFIRM | I19: Au to leach | J19: ='MB Base'!I104 | K19: ='MB Sort'!I104 | L19: =K19-J19 | M19: g/h
B20: Reject rehandle + dump | C20: 2.5 | D20: $/t | G20: Assumption | I20: Au production | J20: =J19*$C$13*$C$11/31.1035 | K20: =K19*$C$13*$C$11/31.1035 | L20: =K20-J20 | M20: oz/a
B21: Sorting OPEX | C21: 0.45 | D21: $/t | F21: STEINERT template ($15/50 t/h + $0.15) | G21: Vendor benchmark
A22: MATERIAL PROPERTY | I22: ECONOMICS (sorting case less base case)
B23: Waste dilution (SLC) | C23: 0.2 | D23: - | F23: sublevel cave, typical 15-25% | G23: Assumption - CONFIRM | I23: Incremental gold to leach | K23: =L19 | M23: g/h
B24: Undiluted ore grade | C24: =C12/(1-C23) | D24: g/t | F24: ROM grade / (1 - dilution) | G24: Calculated | I24: Incremental gold recovered | K24: =L20 | M24: oz/a
B25: Mass yield ore -> scats | C25: 0.1111 | D25: - | F25: calibrated to the measured scat stream | G25: Calibrated | I25: Revenue gain | K25: =L19*C13*C15 | M25: $/h
B26: Mass yield waste -> scats | C26: 0.2 | D26: - | F26: calibrated to the measured scat stream | G26: Calibrated | I26: Sorting OPEX | K26: =-C21*'MB Sort'!G106 | M26: $/h
B27: HETEROGENEITY CONTRAST | C27: =C26/C25 | D27: x | F27: waste yield / ore yield. Sukari = 8.9x | G27: KEY METRIC | I27: Reject rehandle + dump | K27: =-C20*'MB Sort'!G107 | M27: $/h
A28: SORTER PROPERTY | I28: Incremental mining cost | K28: =-C19*L9 | M28: $/h
B29: Sorter ore recovery | C29: 0.95 | D29: - | F29: XRT, conservatively tuned | G29: TEST WORK REQUIRED | I29: Milling cost saved | K29: =-C18*L11 | M29: $/h
B30: Waste mass to rejects | C30: 0.7 | D30: - | F30: XRT on Syama lithologies | G30: TEST WORK REQUIRED | I30: NET CASH BENEFIT | K30: =SUM(K25:K29) | M30: $/h
A31: CAPITAL & EVALUATION | I31: NET CASH BENEFIT | K31: =K30*C11 | M31: $/a
B32: Sorting plant CAPEX | C32: 4095000 | D32: $ | F32: 1 x 50 t/h sorter, STEINERT build-up +30% | G32: Vendor benchmark | I32: NPV | K32: =NPV!B8 | M32: $
B33: Build period | C33: 12 | D33: months | G33: Assumption | I33: IRR | K33: =NPV!B9 | M33: -
B34: Evaluation life | C34: 96 | D34: months | F34: 8 years | G34: Assumption | I34: Simple payback | K34: =IF(K31>0,C32/K31*12,"n/a") | M34: months
B35: ROM feed uplift (Goal Seek) | C35: 7.2 | D35: t/h | F35: Goal Seek: set L17 to 0 by changing this cell | G35: Solved
B36: Capacity capture factor | C36: 1 | D36: - | F36: share of freed SAG capacity actually filled with ore | G36: CRITICAL ASSUMPTION
B37: CALIBRATION CHECK - model must reproduce the measured scat stream
B38: Measured circulating scat load | C38: 30 | D38: t/h | F38: plant survey / client sampling | G38: CLIENT DATA
B39: MEASURED SCAT GRADE | C39: 2 | D39: g/t | F39: plant survey / client sampling | G39: CLIENT DATA
B40: Modelled circulating scat load | C40: ='MB Base'!G106 | D40: t/h | F40: adjust the two mass yields above until modelled = measured | G40: calc
B41: Modelled scat grade | C41: ='MB Base'!H106 | D41: g/t | F41: adjust the two mass yields above until modelled = measured | G41: calc

Sheet MB Base
B1: MB Base | base case - all scats crushed and returned, no sorting
B2: Assumption | C2: Value | D2: Unit | F2: Stream | G2: Mass t/h | H2: Au g/t | I2: Au g/h | J2: Ore % | K2: Ore t/h | L2: Ore g/t | M2: Ore Au g/h | N2: Waste % | O2: Waste t/h
B3: Mass yield ore -> oversize | C3: =Dashboard!C25
B4: Mass yield waste -> oversize | C4: =Dashboard!C26
B5: Sorter ore recovery | C5: 1 | F5: PLANT FEED (new ROM) | G5: =K5+O5 | H5: =IFERROR(I5/G5,0) | I5: =M5 | J5: =IFERROR(K5/G5,0) | K5: =Dashboard!C10*(1-$C$8) | L5: =$C$7 | M5: =K5*L5 | N5: =IFERROR(O5/G5,0) | O5: =Dashboard!C10*$C$8
B6: Waste mass to rejects | C6: 0
B7: Undiluted ore grade | C7: =Dashboard!C24 | D7: g/t
B8: Waste dilution | C8: =Dashboard!C23
F10: RECIRCULATION PASS 1
F11: SAG feed | G11: =K11+O11 | H11: =IFERROR(I11/G11,0) | I11: =M11 | J11: =IFERROR(K11/G11,0) | K11: =K5 | L11: =$C$7 | M11: =K11*L11 | N11: =IFERROR(O11/G11,0) | O11: =O5
F12: SAG discharge | G12: =K12+O12 | H12: =IFERROR(I12/G12,0) | I12: =M12 | J12: =IFERROR(K12/G12,0) | K12: =K11 | L12: =$C$7 | M12: =K12*L12 | N12: =IFERROR(O12/G12,0) | O12: =O11
F13: Mill discharge screen
F14: screen feed | G14: =K14+O14 | H14: =IFERROR(I14/G14,0) | I14: =M14 | J14: =IFERROR(K14/G14,0) | K14: =K12 | L14: =$C$7 | M14: =K14*L14 | N14: =IFERROR(O14/G14,0) | O14: =O12
F15: oversize (scats) | G15: =K15+O15 | H15: =IFERROR(I15/G15,0) | I15: =M15 | J15: =IFERROR(K15/G15,0) | K15: =K14*$C$3 | L15: =$C$7 | M15: =K15*L15 | N15: =IFERROR(O15/G15,0) | O15: =O14*$C$4
F16: undersize | G16: =K16+O16 | H16: =IFERROR(I16/G16,0) | I16: =M16 | J16: =IFERROR(K16/G16,0) | K16: =K14-K15 | L16: =$C$7 | M16: =K16*L16 | N16: =IFERROR(O16/G16,0) | O16: =O14-O15
F17: Pebble sorter
F18: sorter feed | G18: =K18+O18 | H18: =IFERROR(I18/G18,0) | I18: =M18 | J18: =IFERROR(K18/G18,0) | K18: =K15 | L18: =$C$7 | M18: =K18*L18 | N18: =IFERROR(O18/G18,0) | O18: =O15
F19: rejects | G19: =K19+O19 | H19: =IFERROR(I19/G19,0) | I19: =M19 | J19: =IFERROR(K19/G19,0) | K19: =K18*(1-$C$5) | L19: =$C$7 | M19: =K19*L19 | N19: =IFERROR(O19/G19,0) | O19: =O18*$C$6
F20: concentrate -> SAG | G20: =K20+O20 | H20: =IFERROR(I20/G20,0) | I20: =M20 | J20: =IFERROR(K20/G20,0) | K20: =K18-K19 | L20: =$C$7 | M20: =K20*L20 | N20: =IFERROR(O20/G20,0) | O20: =O18-O19
F24: RECIRCULATION PASS 2
F25: SAG feed | G25: =K25+O25 | H25: =IFERROR(I25/G25,0) | I25: =M25 | J25: =IFERROR(K25/G25,0) | K25: =K20 | L25: =$C$7 | M25: =K25*L25 | N25: =IFERROR(O25/G25,0) | O25: =O20
F26: SAG discharge | G26: =K26+O26 | H26: =IFERROR(I26/G26,0) | I26: =M26 | J26: =IFERROR(K26/G26,0) | K26: =K25 | L26: =$C$7 | M26: =K26*L26 | N26: =IFERROR(O26/G26,0) | O26: =O25
F27: Mill discharge screen
F28: screen feed | G28: =K28+O28 | H28: =IFERROR(I28/G28,0) | I28: =M28 | J28: =IFERROR(K28/G28,0) | K28: =K26 | L28: =$C$7 | M28: =K28*L28 | N28: =IFERROR(O28/G28,0) | O28: =O26
F29: oversize (scats) | G29: =K29+O29 | H29: =IFERROR(I29/G29,0) | I29: =M29 | J29: =IFERROR(K29/G29,0) | K29: =K28*$C$3 | L29: =$C$7 | M29: =K29*L29 | N29: =IFERROR(O29/G29,0) | O29: =O28*$C$4
F30: undersize | G30: =K30+O30 | H30: =IFERROR(I30/G30,0) | I30: =M30 | J30: =IFERROR(K30/G30,0) | K30: =K28-K29 | L30: =$C$7 | M30: =K30*L30 | N30: =IFERROR(O30/G30,0) | O30: =O28-O29
F31: Pebble sorter
F32: sorter feed | G32: =K32+O32 | H32: =IFERROR(I32/G32,0) | I32: =M32 | J32: =IFERROR(K32/G32,0) | K32: =K29 | L32: =$C$7 | M32: =K32*L32 | N32: =IFERROR(O32/G32,0) | O32: =O29
F33: rejects | G33: =K33+O33 | H33: =IFERROR(I33/G33,0) | I33: =M33 | J33: =IFERROR(K33/G33,0) | K33: =K32*(1-$C$5) | L33: =$C$7 | M33: =K33*L33 | N33: =IFERROR(O33/G33,0) | O33: =O32*$C$6
F34: concentrate -> SAG | G34: =K34+O34 | H34: =IFERROR(I34/G34,0) | I34: =M34 | J34: =IFERROR(K34/G34,0) | K34: =K32-K33 | L34: =$C$7 | M34: =K34*L34 | N34: =IFERROR(O34/G34,0) | O34: =O32-O33
F38: RECIRCULATION PASS 3
F39: SAG feed | G39: =K39+O39 | H39: =IFERROR(I39/G39,0) | I39: =M39 | J39: =IFERROR(K39/G39,0) | K39: =K34 | L39: =$C$7 | M39: =K39*L39 | N39: =IFERROR(O39/G39,0) | O39: =O34
F40: SAG discharge | G40: =K40+O40 | H40: =IFERROR(I40/G40,0) | I40: =M40 | J40: =IFERROR(K40/G40,0) | K40: =K39 | L40: =$C$7 | M40: =K40*L40 | N40: =IFERROR(O40/G40,0) | O40: =O39
F41: Mill discharge screen
F42: screen feed | G42: =K42+O42 | H42: =IFERROR(I42/G42,0) | I42: =M42 | J42: =IFERROR(K42/G42,0) | K42: =K40 | L42: =$C$7 | M42: =K42*L42 | N42: =IFERROR(O42/G42,0) | O42: =O40
F43: oversize (scats) | G43: =K43+O43 | H43: =IFERROR(I43/G43,0) | I43: =M43 | J43: =IFERROR(K43/G43,0) | K43: =K42*$C$3 | L43: =$C$7 | M43: =K43*L43 | N43: =IFERROR(O43/G43,0) | O43: =O42*$C$4
F44: undersize | G44: =K44+O44 | H44: =IFERROR(I44/G44,0) | I44: =M44 | J44: =IFERROR(K44/G44,0) | K44: =K42-K43 | L44: =$C$7 | M44: =K44*L44 | N44: =IFERROR(O44/G44,0) | O44: =O42-O43
F45: Pebble sorter
F46: sorter feed | G46: =K46+O46 | H46: =IFERROR(I46/G46,0) | I46: =M46 | J46: =IFERROR(K46/G46,0) | K46: =K43 | L46: =$C$7 | M46: =K46*L46 | N46: =IFERROR(O46/G46,0) | O46: =O43
F47: rejects | G47: =K47+O47 | H47: =IFERROR(I47/G47,0) | I47: =M47 | J47: =IFERROR(K47/G47,0) | K47: =K46*(1-$C$5) | L47: =$C$7 | M47: =K47*L47 | N47: =IFERROR(O47/G47,0) | O47: =O46*$C$6
F48: concentrate -> SAG | G48: =K48+O48 | H48: =IFERROR(I48/G48,0) | I48: =M48 | J48: =IFERROR(K48/G48,0) | K48: =K46-K47 | L48: =$C$7 | M48: =K48*L48 | N48: =IFERROR(O48/G48,0) | O48: =O46-O47
F52: RECIRCULATION PASS 4
F53: SAG feed | G53: =K53+O53 | H53: =IFERROR(I53/G53,0) | I53: =M53 | J53: =IFERROR(K53/G53,0) | K53: =K48 | L53: =$C$7 | M53: =K53*L53 | N53: =IFERROR(O53/G53,0) | O53: =O48
F54: SAG discharge | G54: =K54+O54 | H54: =IFERROR(I54/G54,0) | I54: =M54 | J54: =IFERROR(K54/G54,0) | K54: =K53 | L54: =$C$7 | M54: =K54*L54 | N54: =IFERROR(O54/G54,0) | O54: =O53
F55: Mill discharge screen
F56: screen feed | G56: =K56+O56 | H56: =IFERROR(I56/G56,0) | I56: =M56 | J56: =IFERROR(K56/G56,0) | K56: =K54 | L56: =$C$7 | M56: =K56*L56 | N56: =IFERROR(O56/G56,0) | O56: =O54
F57: oversize (scats) | G57: =K57+O57 | H57: =IFERROR(I57/G57,0) | I57: =M57 | J57: =IFERROR(K57/G57,0) | K57: =K56*$C$3 | L57: =$C$7 | M57: =K57*L57 | N57: =IFERROR(O57/G57,0) | O57: =O56*$C$4
F58: undersize | G58: =K58+O58 | H58: =IFERROR(I58/G58,0) | I58: =M58 | J58: =IFERROR(K58/G58,0) | K58: =K56-K57 | L58: =$C$7 | M58: =K58*L58 | N58: =IFERROR(O58/G58,0) | O58: =O56-O57
F59: Pebble sorter
F60: sorter feed | G60: =K60+O60 | H60: =IFERROR(I60/G60,0) | I60: =M60 | J60: =IFERROR(K60/G60,0) | K60: =K57 | L60: =$C$7 | M60: =K60*L60 | N60: =IFERROR(O60/G60,0) | O60: =O57
F61: rejects | G61: =K61+O61 | H61: =IFERROR(I61/G61,0) | I61: =M61 | J61: =IFERROR(K61/G61,0) | K61: =K60*(1-$C$5) | L61: =$C$7 | M61: =K61*L61 | N61: =IFERROR(O61/G61,0) | O61: =O60*$C$6
F62: concentrate -> SAG | G62: =K62+O62 | H62: =IFERROR(I62/G62,0) | I62: =M62 | J62: =IFERROR(K62/G62,0) | K62: =K60-K61 | L62: =$C$7 | M62: =K62*L62 | N62: =IFERROR(O62/G62,0) | O62: =O60-O61
F66: RECIRCULATION PASS 5
F67: SAG feed | G67: =K67+O67 | H67: =IFERROR(I67/G67,0) | I67: =M67 | J67: =IFERROR(K67/G67,0) | K67: =K62 | L67: =$C$7 | M67: =K67*L67 | N67: =IFERROR(O67/G67,0) | O67: =O62
F68: SAG discharge | G68: =K68+O68 | H68: =IFERROR(I68/G68,0) | I68: =M68 | J68: =IFERROR(K68/G68,0) | K68: =K67 | L68: =$C$7 | M68: =K68*L68 | N68: =IFERROR(O68/G68,0) | O68: =O67
F69: Mill discharge screen
F70: screen feed | G70: =K70+O70 | H70: =IFERROR(I70/G70,0) | I70: =M70 | J70: =IFERROR(K70/G70,0) | K70: =K68 | L70: =$C$7 | M70: =K70*L70 | N70: =IFERROR(O70/G70,0) | O70: =O68
F71: oversize (scats) | G71: =K71+O71 | H71: =IFERROR(I71/G71,0) | I71: =M71 | J71: =IFERROR(K71/G71,0) | K71: =K70*$C$3 | L71: =$C$7 | M71: =K71*L71 | N71: =IFERROR(O71/G71,0) | O71: =O70*$C$4
F72: undersize | G72: =K72+O72 | H72: =IFERROR(I72/G72,0) | I72: =M72 | J72: =IFERROR(K72/G72,0) | K72: =K70-K71 | L72: =$C$7 | M72: =K72*L72 | N72: =IFERROR(O72/G72,0) | O72: =O70-O71
F73: Pebble sorter
F74: sorter feed | G74: =K74+O74 | H74: =IFERROR(I74/G74,0) | I74: =M74 | J74: =IFERROR(K74/G74,0) | K74: =K71 | L74: =$C$7 | M74: =K74*L74 | N74: =IFERROR(O74/G74,0) | O74: =O71
F75: rejects | G75: =K75+O75 | H75: =IFERROR(I75/G75,0) | I75: =M75 | J75: =IFERROR(K75/G75,0) | K75: =K74*(1-$C$5) | L75: =$C$7 | M75: =K75*L75 | N75: =IFERROR(O75/G75,0) | O75: =O74*$C$6
F76: concentrate -> SAG | G76: =K76+O76 | H76: =IFERROR(I76/G76,0) | I76: =M76 | J76: =IFERROR(K76/G76,0) | K76: =K74-K75 | L76: =$C$7 | M76: =K76*L76 | N76: =IFERROR(O76/G76,0) | O76: =O74-O75
F80: RECIRCULATION PASS 6
F81: SAG feed | G81: =K81+O81 | H81: =IFERROR(I81/G81,0) | I81: =M81 | J81: =IFERROR(K81/G81,0) | K81: =K76 | L81: =$C$7 | M81: =K81*L81 | N81: =IFERROR(O81/G81,0) | O81: =O76
F82: SAG discharge | G82: =K82+O82 | H82: =IFERROR(I82/G82,0) | I82: =M82 | J82: =IFERROR(K82/G82,0) | K82: =K81 | L82: =$C$7 | M82: =K82*L82 | N82: =IFERROR(O82/G82,0) | O82: =O81
F83: Mill discharge screen
F84: screen feed | G84: =K84+O84 | H84: =IFERROR(I84/G84,0) | I84: =M84 | J84: =IFERROR(K84/G84,0) | K84: =K82 | L84: =$C$7 | M84: =K84*L84 | N84: =IFERROR(O84/G84,0) | O84: =O82
F85: oversize (scats) | G85: =K85+O85 | H85: =IFERROR(I85/G85,0) | I85: =M85 | J85: =IFERROR(K85/G85,0) | K85: =K84*$C$3 | L85: =$C$7 | M85: =K85*L85 | N85: =IFERROR(O85/G85,0) | O85: =O84*$C$4
F86: undersize | G86: =K86+O86 | H86: =IFERROR(I86/G86,0) | I86: =M86 | J86: =IFERROR(K86/G86,0) | K86: =K84-K85 | L86: =$C$7 | M86: =K86*L86 | N86: =IFERROR(O86/G86,0) | O86: =O84-O85
F87: Pebble sorter
F88: sorter feed | G88: =K88+O88 | H88: =IFERROR(I88/G88,0) | I88: =M88 | J88: =IFERROR(K88/G88,0) | K88: =K85 | L88: =$C$7 | M88: =K88*L88 | N88: =IFERROR(O88/G88,0) | O88: =O85
F89: rejects | G89: =K89+O89 | H89: =IFERROR(I89/G89,0) | I89: =M89 | J89: =IFERROR(K89/G89,0) | K89: =K88*(1-$C$5) | L89: =$C$7 | M89: =K89*L89 | N89: =IFERROR(O89/G89,0) | O89: =O88*$C$6
F90: concentrate -> SAG | G90: =K90+O90 | H90: =IFERROR(I90/G90,0) | I90: =M90 | J90: =IFERROR(K90/G90,0) | K90: =K88-K89 | L90: =$C$7 | M90: =K90*L90 | N90: =IFERROR(O90/G90,0) | O90: =O88-O89
F98: CIRCUIT TOTAL
F99: SAG MILL FEED (total load) | G99: =K99+O99 | H99: =IFERROR(I99/G99,0) | I99: =M99 | J99: =IFERROR(K99/G99,0) | K99: =K11+K25+K39+K53+K67+K81 | L99: =$C$7 | M99: =K99*L99 | N99: =IFERROR(O99/G99,0) | O99: =O11+O25+O39+O53+O67+O81
F100: SAG mill discharge | G100: =K100+O100 | H100: =IFERROR(I100/G100,0) | I100: =M100 | J100: =IFERROR(K100/G100,0) | K100: =K99 | L100: =$C$7 | M100: =K100*L100 | N100: =IFERROR(O100/G100,0) | O100: =O99
F101: Mill discharge screen
F102: screen feed | G102: =K102+O102 | H102: =IFERROR(I102/G102,0) | I102: =M102 | J102: =IFERROR(K102/G102,0) | K102: =K100 | L102: =$C$7 | M102: =K102*L102 | N102: =IFERROR(O102/G102,0) | O102: =O100
F103: oversize (scats) | G103: =K103+O103 | H103: =IFERROR(I103/G103,0) | I103: =M103 | J103: =IFERROR(K103/G103,0) | K103: =K102*$C$3 | L103: =$C$7 | M103: =K103*L103 | N103: =IFERROR(O103/G103,0) | O103: =O102*$C$4
F104: UNDERSIZE -> ball mill / leach | G104: =K104+O104 | H104: =IFERROR(I104/G104,0) | I104: =M104 | J104: =IFERROR(K104/G104,0) | K104: =K102-K103 | L104: =$C$7 | M104: =K104*L104 | N104: =IFERROR(O104/G104,0) | O104: =O102-O103
F105: Pebble sorter
F106: SORTER FEED | G106: =K106+O106 | H106: =IFERROR(I106/G106,0) | I106: =M106 | J106: =IFERROR(K106/G106,0) | K106: =K103 | L106: =$C$7 | M106: =K106*L106 | N106: =IFERROR(O106/G106,0) | O106: =O103
F107: REJECTS -> waste dump | G107: =K107+O107 | H107: =IFERROR(I107/G107,0) | I107: =M107 | J107: =IFERROR(K107/G107,0) | K107: =K106*(1-$C$5) | L107: =$C$7 | M107: =K107*L107 | N107: =IFERROR(O107/G107,0) | O107: =O106*$C$6
F108: CONCENTRATE -> SAG | G108: =K108+O108 | H108: =IFERROR(I108/G108,0) | I108: =M108 | J108: =IFERROR(K108/G108,0) | K108: =K106-K107 | L108: =$C$7 | M108: =K108*L108 | N108: =IFERROR(O108/G108,0) | O108: =O106-O107
B111: SORTER PERFORMANCE
B112: Mass pull to rejects | C112: =IFERROR(G107/G106,0)
B113: Au recovery to concentrate | C113: =IFERROR(I108/I106,1)
B114: Upgrade ratio (conc / feed) | C114: =IFERROR(H108/H106,1) | D114: x
B115: Au lost to rejects | C115: =I107 | D115: g/h
B116: Recoverable value discarded | C116: =I107*Dashboard!C13*Dashboard!C15 | D116: $/h
B117: In-situ value of reject stream | C117: =H107*Dashboard!C13*Dashboard!C15 | D117: $/t
B118: Cost avoided per reject tonne | C118: =Dashboard!C18-Dashboard!C20 | D118: $/t

Sheet MB Sort
B1: MB Sort | sorting case - barren scat mass rejected, freed SAG capacity refilled with ROM
B2: Assumption | C2: Value | D2: Unit | F2: Stream | G2: Mass t/h | H2: Au g/t | I2: Au g/h | J2: Ore % | K2: Ore t/h | L2: Ore g/t | M2: Ore Au g/h | N2: Waste % | O2: Waste t/h
B3: Mass yield ore -> oversize | C3: =Dashboard!C25
B4: Mass yield waste -> oversize | C4: =Dashboard!C26
B5: Sorter ore recovery | C5: =Dashboard!C29 | F5: PLANT FEED (new ROM) | G5: =K5+O5 | H5: =IFERROR(I5/G5,0) | I5: =M5 | J5: =IFERROR(K5/G5,0) | K5: =(Dashboard!C10+Dashboard!C35*Dashboard!C36)*(1-$C$8) | L5: =$C$7 | M5: =K5*L5 | N5: =IFERROR(O5/G5,0) | O5: =(Dashboard!C10+Dashboard!C35*Dashboard!C36)*$C$8
B6: Waste mass to rejects | C6: =Dashboard!C30
B7: Undiluted ore grade | C7: =Dashboard!C24 | D7: g/t
B8: Waste dilution | C8: =Dashboard!C23
F10: RECIRCULATION PASS 1
F11: SAG feed | G11: =K11+O11 | H11: =IFERROR(I11/G11,0) | I11: =M11 | J11: =IFERROR(K11/G11,0) | K11: =K5 | L11: =$C$7 | M11: =K11*L11 | N11: =IFERROR(O11/G11,0) | O11: =O5
F12: SAG discharge | G12: =K12+O12 | H12: =IFERROR(I12/G12,0) | I12: =M12 | J12: =IFERROR(K12/G12,0) | K12: =K11 | L12: =$C$7 | M12: =K12*L12 | N12: =IFERROR(O12/G12,0) | O12: =O11
F13: Mill discharge screen
F14: screen feed | G14: =K14+O14 | H14: =IFERROR(I14/G14,0) | I14: =M14 | J14: =IFERROR(K14/G14,0) | K14: =K12 | L14: =$C$7 | M14: =K14*L14 | N14: =IFERROR(O14/G14,0) | O14: =O12
F15: oversize (scats) | G15: =K15+O15 | H15: =IFERROR(I15/G15,0) | I15: =M15 | J15: =IFERROR(K15/G15,0) | K15: =K14*$C$3 | L15: =$C$7 | M15: =K15*L15 | N15: =IFERROR(O15/G15,0) | O15: =O14*$C$4
F16: undersize | G16: =K16+O16 | H16: =IFERROR(I16/G16,0) | I16: =M16 | J16: =IFERROR(K16/G16,0) | K16: =K14-K15 | L16: =$C$7 | M16: =K16*L16 | N16: =IFERROR(O16/G16,0) | O16: =O14-O15
F17: Pebble sorter
F18: sorter feed | G18: =K18+O18 | H18: =IFERROR(I18/G18,0) | I18: =M18 | J18: =IFERROR(K18/G18,0) | K18: =K15 | L18: =$C$7 | M18: =K18*L18 | N18: =IFERROR(O18/G18,0) | O18: =O15
F19: rejects | G19: =K19+O19 | H19: =IFERROR(I19/G19,0) | I19: =M19 | J19: =IFERROR(K19/G19,0) | K19: =K18*(1-$C$5) | L19: =$C$7 | M19: =K19*L19 | N19: =IFERROR(O19/G19,0) | O19: =O18*$C$6
F20: concentrate -> SAG | G20: =K20+O20 | H20: =IFERROR(I20/G20,0) | I20: =M20 | J20: =IFERROR(K20/G20,0) | K20: =K18-K19 | L20: =$C$7 | M20: =K20*L20 | N20: =IFERROR(O20/G20,0) | O20: =O18-O19
F24: RECIRCULATION PASS 2
F25: SAG feed | G25: =K25+O25 | H25: =IFERROR(I25/G25,0) | I25: =M25 | J25: =IFERROR(K25/G25,0) | K25: =K20 | L25: =$C$7 | M25: =K25*L25 | N25: =IFERROR(O25/G25,0) | O25: =O20
F26: SAG discharge | G26: =K26+O26 | H26: =IFERROR(I26/G26,0) | I26: =M26 | J26: =IFERROR(K26/G26,0) | K26: =K25 | L26: =$C$7 | M26: =K26*L26 | N26: =IFERROR(O26/G26,0) | O26: =O25
F27: Mill discharge screen
F28: screen feed | G28: =K28+O28 | H28: =IFERROR(I28/G28,0) | I28: =M28 | J28: =IFERROR(K28/G28,0) | K28: =K26 | L28: =$C$7 | M28: =K28*L28 | N28: =IFERROR(O28/G28,0) | O28: =O26
F29: oversize (scats) | G29: =K29+O29 | H29: =IFERROR(I29/G29,0) | I29: =M29 | J29: =IFERROR(K29/G29,0) | K29: =K28*$C$3 | L29: =$C$7 | M29: =K29*L29 | N29: =IFERROR(O29/G29,0) | O29: =O28*$C$4
F30: undersize | G30: =K30+O30 | H30: =IFERROR(I30/G30,0) | I30: =M30 | J30: =IFERROR(K30/G30,0) | K30: =K28-K29 | L30: =$C$7 | M30: =K30*L30 | N30: =IFERROR(O30/G30,0) | O30: =O28-O29
F31: Pebble sorter
F32: sorter feed | G32: =K32+O32 | H32: =IFERROR(I32/G32,0) | I32: =M32 | J32: =IFERROR(K32/G32,0) | K32: =K29 | L32: =$C$7 | M32: =K32*L32 | N32: =IFERROR(O32/G32,0) | O32: =O29
F33: rejects | G33: =K33+O33 | H33: =IFERROR(I33/G33,0) | I33: =M33 | J33: =IFERROR(K33/G33,0) | K33: =K32*(1-$C$5) | L33: =$C$7 | M33: =K33*L33 | N33: =IFERROR(O33/G33,0) | O33: =O32*$C$6
F34: concentrate -> SAG | G34: =K34+O34 | H34: =IFERROR(I34/G34,0) | I34: =M34 | J34: =IFERROR(K34/G34,0) | K34: =K32-K33 | L34: =$C$7 | M34: =K34*L34 | N34: =IFERROR(O34/G34,0) | O34: =O32-O33
F38: RECIRCULATION PASS 3
F39: SAG feed | G39: =K39+O39 | H39: =IFERROR(I39/G39,0) | I39: =M39 | J39: =IFERROR(K39/G39,0) | K39: =K34 | L39: =$C$7 | M39: =K39*L39 | N39: =IFERROR(O39/G39,0) | O39: =O34
F40: SAG discharge | G40: =K40+O40 | H40: =IFERROR(I40/G40,0) | I40: =M40 | J40: =IFERROR(K40/G40,0) | K40: =K39 | L40: =$C$7 | M40: =K40*L40 | N40: =IFERROR(O40/G40,0) | O40: =O39
F41: Mill discharge screen
F42: screen feed | G42: =K42+O42 | H42: =IFERROR(I42/G42,0) | I42: =M42 | J42: =IFERROR(K42/G42,0) | K42: =K40 | L42: =$C$7 | M42: =K42*L42 | N42: =IFERROR(O42/G42,0) | O42: =O40
F43: oversize (scats) | G43: =K43+O43 | H43: =IFERROR(I43/G43,0) | I43: =M43 | J43: =IFERROR(K43/G43,0) | K43: =K42*$C$3 | L43: =$C$7 | M43: =K43*L43 | N43: =IFERROR(O43/G43,0) | O43: =O42*$C$4
F44: undersize | G44: =K44+O44 | H44: =IFERROR(I44/G44,0) | I44: =M44 | J44: =IFERROR(K44/G44,0) | K44: =K42-K43 | L44: =$C$7 | M44: =K44*L44 | N44: =IFERROR(O44/G44,0) | O44: =O42-O43
F45: Pebble sorter
F46: sorter feed | G46: =K46+O46 | H46: =IFERROR(I46/G46,0) | I46: =M46 | J46: =IFERROR(K46/G46,0) | K46: =K43 | L46: =$C$7 | M46: =K46*L46 | N46: =IFERROR(O46/G46,0) | O46: =O43
F47: rejects | G47: =K47+O47 | H47: =IFERROR(I47/G47,0) | I47: =M47 | J47: =IFERROR(K47/G47,0) | K47: =K46*(1-$C$5) | L47: =$C$7 | M47: =K47*L47 | N47: =IFERROR(O47/G47,0) | O47: =O46*$C$6
F48: concentrate -> SAG | G48: =K48+O48 | H48: =IFERROR(I48/G48,0) | I48: =M48 | J48: =IFERROR(K48/G48,0) | K48: =K46-K47 | L48: =$C$7 | M48: =K48*L48 | N48: =IFERROR(O48/G48,0) | O48: =O46-O47
F52: RECIRCULATION PASS 4
F53: SAG feed | G53: =K53+O53 | H53: =IFERROR(I53/G53,0) | I53: =M53 | J53: =IFERROR(K53/G53,0) | K53: =K48 | L53: =$C$7 | M53: =K53*L53 | N53: =IFERROR(O53/G53,0) | O53: =O48
F54: SAG discharge | G54: =K54+O54 | H54: =IFERROR(I54/G54,0) | I54: =M54 | J54: =IFERROR(K54/G54,0) | K54: =K53 | L54: =$C$7 | M54: =K54*L54 | N54: =IFERROR(O54/G54,0) | O54: =O53
F55: Mill discharge screen
F56: screen feed | G56: =K56+O56 | H56: =IFERROR(I56/G56,0) | I56: =M56 | J56: =IFERROR(K56/G56,0) | K56: =K54 | L56: =$C$7 | M56: =K56*L56 | N56: =IFERROR(O56/G56,0) | O56: =O54
F57: oversize (scats) | G57: =K57+O57 | H57: =IFERROR(I57/G57,0) | I57: =M57 | J57: =IFERROR(K57/G57,0) | K57: =K56*$C$3 | L57: =$C$7 | M57: =K57*L57 | N57: =IFERROR(O57/G57,0) | O57: =O56*$C$4
F58: undersize | G58: =K58+O58 | H58: =IFERROR(I58/G58,0) | I58: =M58 | J58: =IFERROR(K58/G58,0) | K58: =K56-K57 | L58: =$C$7 | M58: =K58*L58 | N58: =IFERROR(O58/G58,0) | O58: =O56-O57
F59: Pebble sorter
F60: sorter feed | G60: =K60+O60 | H60: =IFERROR(I60/G60,0) | I60: =M60 | J60: =IFERROR(K60/G60,0) | K60: =K57 | L60: =$C$7 | M60: =K60*L60 | N60: =IFERROR(O60/G60,0) | O60: =O57
F61: rejects | G61: =K61+O61 | H61: =IFERROR(I61/G61,0) | I61: =M61 | J61: =IFERROR(K61/G61,0) | K61: =K60*(1-$C$5) | L61: =$C$7 | M61: =K61*L61 | N61: =IFERROR(O61/G61,0) | O61: =O60*$C$6
F62: concentrate -> SAG | G62: =K62+O62 | H62: =IFERROR(I62/G62,0) | I62: =M62 | J62: =IFERROR(K62/G62,0) | K62: =K60-K61 | L62: =$C$7 | M62: =K62*L62 | N62: =IFERROR(O62/G62,0) | O62: =O60-O61
F66: RECIRCULATION PASS 5
F67: SAG feed | G67: =K67+O67 | H67: =IFERROR(I67/G67,0) | I67: =M67 | J67: =IFERROR(K67/G67,0) | K67: =K62 | L67: =$C$7 | M67: =K67*L67 | N67: =IFERROR(O67/G67,0) | O67: =O62
F68: SAG discharge | G68: =K68+O68 | H68: =IFERROR(I68/G68,0) | I68: =M68 | J68: =IFERROR(K68/G68,0) | K68: =K67 | L68: =$C$7 | M68: =K68*L68 | N68: =IFERROR(O68/G68,0) | O68: =O67
F69: Mill discharge screen
F70: screen feed | G70: =K70+O70 | H70: =IFERROR(I70/G70,0) | I70: =M70 | J70: =IFERROR(K70/G70,0) | K70: =K68 | L70: =$C$7 | M70: =K70*L70 | N70: =IFERROR(O70/G70,0) | O70: =O68
F71: oversize (scats) | G71: =K71+O71 | H71: =IFERROR(I71/G71,0) | I71: =M71 | J71: =IFERROR(K71/G71,0) | K71: =K70*$C$3 | L71: =$C$7 | M71: =K71*L71 | N71: =IFERROR(O71/G71,0) | O71: =O70*$C$4
F72: undersize | G72: =K72+O72 | H72: =IFERROR(I72/G72,0) | I72: =M72 | J72: =IFERROR(K72/G72,0) | K72: =K70-K71 | L72: =$C$7 | M72: =K72*L72 | N72: =IFERROR(O72/G72,0) | O72: =O70-O71
F73: Pebble sorter
F74: sorter feed | G74: =K74+O74 | H74: =IFERROR(I74/G74,0) | I74: =M74 | J74: =IFERROR(K74/G74,0) | K74: =K71 | L74: =$C$7 | M74: =K74*L74 | N74: =IFERROR(O74/G74,0) | O74: =O71
F75: rejects | G75: =K75+O75 | H75: =IFERROR(I75/G75,0) | I75: =M75 | J75: =IFERROR(K75/G75,0) | K75: =K74*(1-$C$5) | L75: =$C$7 | M75: =K75*L75 | N75: =IFERROR(O75/G75,0) | O75: =O74*$C$6
F76: concentrate -> SAG | G76: =K76+O76 | H76: =IFERROR(I76/G76,0) | I76: =M76 | J76: =IFERROR(K76/G76,0) | K76: =K74-K75 | L76: =$C$7 | M76: =K76*L76 | N76: =IFERROR(O76/G76,0) | O76: =O74-O75
F80: RECIRCULATION PASS 6
F81: SAG feed | G81: =K81+O81 | H81: =IFERROR(I81/G81,0) | I81: =M81 | J81: =IFERROR(K81/G81,0) | K81: =K76 | L81: =$C$7 | M81: =K81*L81 | N81: =IFERROR(O81/G81,0) | O81: =O76
F82: SAG discharge | G82: =K82+O82 | H82: =IFERROR(I82/G82,0) | I82: =M82 | J82: =IFERROR(K82/G82,0) | K82: =K81 | L82: =$C$7 | M82: =K82*L82 | N82: =IFERROR(O82/G82,0) | O82: =O81
F83: Mill discharge screen
F84: screen feed | G84: =K84+O84 | H84: =IFERROR(I84/G84,0) | I84: =M84 | J84: =IFERROR(K84/G84,0) | K84: =K82 | L84: =$C$7 | M84: =K84*L84 | N84: =IFERROR(O84/G84,0) | O84: =O82
F85: oversize (scats) | G85: =K85+O85 | H85: =IFERROR(I85/G85,0) | I85: =M85 | J85: =IFERROR(K85/G85,0) | K85: =K84*$C$3 | L85: =$C$7 | M85: =K85*L85 | N85: =IFERROR(O85/G85,0) | O85: =O84*$C$4
F86: undersize | G86: =K86+O86 | H86: =IFERROR(I86/G86,0) | I86: =M86 | J86: =IFERROR(K86/G86,0) | K86: =K84-K85 | L86: =$C$7 | M86: =K86*L86 | N86: =IFERROR(O86/G86,0) | O86: =O84-O85
F87: Pebble sorter
F88: sorter feed | G88: =K88+O88 | H88: =IFERROR(I88/G88,0) | I88: =M88 | J88: =IFERROR(K88/G88,0) | K88: =K85 | L88: =$C$7 | M88: =K88*L88 | N88: =IFERROR(O88/G88,0) | O88: =O85
F89: rejects | G89: =K89+O89 | H89: =IFERROR(I89/G89,0) | I89: =M89 | J89: =IFERROR(K89/G89,0) | K89: =K88*(1-$C$5) | L89: =$C$7 | M89: =K89*L89 | N89: =IFERROR(O89/G89,0) | O89: =O88*$C$6
F90: concentrate -> SAG | G90: =K90+O90 | H90: =IFERROR(I90/G90,0) | I90: =M90 | J90: =IFERROR(K90/G90,0) | K90: =K88-K89 | L90: =$C$7 | M90: =K90*L90 | N90: =IFERROR(O90/G90,0) | O90: =O88-O89
F98: CIRCUIT TOTAL
F99: SAG MILL FEED (total load) | G99: =K99+O99 | H99: =IFERROR(I99/G99,0) | I99: =M99 | J99: =IFERROR(K99/G99,0) | K99: =K11+K25+K39+K53+K67+K81 | L99: =$C$7 | M99: =K99*L99 | N99: =IFERROR(O99/G99,0) | O99: =O11+O25+O39+O53+O67+O81
F100: SAG mill discharge | G100: =K100+O100 | H100: =IFERROR(I100/G100,0) | I100: =M100 | J100: =IFERROR(K100/G100,0) | K100: =K99 | L100: =$C$7 | M100: =K100*L100 | N100: =IFERROR(O100/G100,0) | O100: =O99
F101: Mill discharge screen
F102: screen feed | G102: =K102+O102 | H102: =IFERROR(I102/G102,0) | I102: =M102 | J102: =IFERROR(K102/G102,0) | K102: =K100 | L102: =$C$7 | M102: =K102*L102 | N102: =IFERROR(O102/G102,0) | O102: =O100
F103: oversize (scats) | G103: =K103+O103 | H103: =IFERROR(I103/G103,0) | I103: =M103 | J103: =IFERROR(K103/G103,0) | K103: =K102*$C$3 | L103: =$C$7 | M103: =K103*L103 | N103: =IFERROR(O103/G103,0) | O103: =O102*$C$4
F104: UNDERSIZE -> ball mill / leach | G104: =K104+O104 | H104: =IFERROR(I104/G104,0) | I104: =M104 | J104: =IFERROR(K104/G104,0) | K104: =K102-K103 | L104: =$C$7 | M104: =K104*L104 | N104: =IFERROR(O104/G104,0) | O104: =O102-O103
F105: Pebble sorter
F106: SORTER FEED | G106: =K106+O106 | H106: =IFERROR(I106/G106,0) | I106: =M106 | J106: =IFERROR(K106/G106,0) | K106: =K103 | L106: =$C$7 | M106: =K106*L106 | N106: =IFERROR(O106/G106,0) | O106: =O103
F107: REJECTS -> waste dump | G107: =K107+O107 | H107: =IFERROR(I107/G107,0) | I107: =M107 | J107: =IFERROR(K107/G107,0) | K107: =K106*(1-$C$5) | L107: =$C$7 | M107: =K107*L107 | N107: =IFERROR(O107/G107,0) | O107: =O106*$C$6
F108: CONCENTRATE -> SAG | G108: =K108+O108 | H108: =IFERROR(I108/G108,0) | I108: =M108 | J108: =IFERROR(K108/G108,0) | K108: =K106-K107 | L108: =$C$7 | M108: =K108*L108 | N108: =IFERROR(O108/G108,0) | O108: =O106-O107
B111: SORTER PERFORMANCE
B112: Mass pull to rejects | C112: =IFERROR(G107/G106,0)
B113: Au recovery to concentrate | C113: =IFERROR(I108/I106,1)
B114: Upgrade ratio (conc / feed) | C114: =IFERROR(H108/H106,1) | D114: x
B115: Au lost to rejects | C115: =I107 | D115: g/h
B116: Recoverable value discarded | C116: =I107*Dashboard!C13*Dashboard!C15 | D116: $/h
B117: In-situ value of reject stream | C117: =H107*Dashboard!C13*Dashboard!C15 | D117: $/t
B118: Cost avoided per reject tonne | C118: =Dashboard!C18-Dashboard!C20 | D118: $/t

Sheet NPV
A1: NPV | monthly cash flow
A3: CAPEX | B3: =Dashboard!C32 | C3: $
A4: Net benefit | B4: =Dashboard!K31 | C4: $/a
A5: Discount rate | B5: =Dashboard!C16
A6: Build period | B6: =Dashboard!C33 | C6: months
A7: Evaluation life | B7: =Dashboard!C34 | C7: months
A8: NPV | B8: =NPV(B5/12,D13:DS13) | C8: $
A9: IRR (annualised) | B9: =IFERROR((1+IRR(D13:DS13))^12-1,"n/a")
A10: Simple payback | B10: =IF(B4>0,B3/B4*12,"n/a") | C10: months
A12: Month | D12: 1 | E12: 2 | F12: 3 | G12: 4 | H12: 5 | I12: 6 | J12: 7 | K12: 8 | L12: 9 | M12: 10 | N12: 11 | O12: 12 | P12: 13 | Q12: 14 | R12: 15 | S12: 16 | T12: 17 | U12: 18 | V12: 19 | W12: 20 | X12: 21 | Y12: 22 | Z12: 23 | AA12: 24 | AB12: 25 | AC12: 26 | AD12: 27 | AE12: 28 | AF12: 29 | AG12: 30 | AH12: 31 | AI12: 32 | AJ12: 33 | AK12: 34 | AL12: 35 | AM12: 36 | AN12: 37 | AO12: 38 | AP12: 39 | AQ12: 40 | AR12: 41 | AS12: 42 | AT12: 43 | AU12: 44 | AV12: 45 | AW12: 46 | AX12: 47 | AY12: 48 | AZ12: 49 | BA12: 50 | BB12: 51 | BC12: 52 | BD12: 53 | BE12: 54 | BF12: 55 | BG12: 56 | BH12: 57 | BI12: 58 | BJ12: 59 | BK12: 60 | BL12: 61 | BM12: 62 | BN12: 63 | BO12: 64 | BP12: 65 | BQ12: 66 | BR12: 67 | BS12: 68 | BT12: 69 | BU12: 70 | BV12: 71 | BW12: 72 | BX12: 73 | BY12: 74 | BZ12: 75 | CA12: 76 | CB12: 77 | CC12: 78 | CD12: 79 | CE12: 80 | CF12: 81 | CG12: 82 | CH12: 83 | CI12: 84 | CJ12: 85 | CK12: 86 | CL12: 87 | CM12: 88 | CN12: 89 | CO12: 90 | CP12: 91 | CQ12: 92 | CR12: 93 | CS12: 94 | CT12: 95 | CU12: 96 | CV12: 97 | CW12: 98 | CX12: 99 | CY12: 100 | CZ12: 101 | DA12: 102 | DB12: 103 | DC12: 104 | DD12: 105 | DE12: 106 | DF12: 107 | DG12: 108 | DH12: 109 | DI12: 110 | DJ12: 111 | DK12: 112 | DL12: 113 | DM12: 114 | DN12: 115 | DO12: 116 | DP12: 117 | DQ12: 118 | DR12: 119 | DS12: 120
A13: Net cash flow | D13: =IF(D$12=1,-$B$3,0)+IF(AND(D$12>$B$6,D$12<=$B$6+$B$7),$B$4/12,0) | E13: =IF(E$12=1,-$B$3,0)+IF(AND(E$12>$B$6,E$12<=$B$6+$B$7),$B$4/12,0) | F13: =IF(F$12=1,-$B$3,0)+IF(AND(F$12>$B$6,F$12<=$B$6+$B$7),$B$4/12,0) | G13: =IF(G$12=1,-$B$3,0)+IF(AND(G$12>$B$6,G$12<=$B$6+$B$7),$B$4/12,0) | H13: =IF(H$12=1,-$B$3,0)+IF(AND(H$12>$B$6,H$12<=$B$6+$B$7),$B$4/12,0) | I13: =IF(I$12=1,-$B$3,0)+IF(AND(I$12>$B$6,I$12<=$B$6+$B$7),$B$4/12,0) | J13: =IF(J$12=1,-$B$3,0)+IF(AND(J$12>$B$6,J$12<=$B$6+$B$7),$B$4/12,0) | K13: =IF(K$12=1,-$B$3,0)+IF(AND(K$12>$B$6,K$12<=$B$6+$B$7),$B$4/12,0) | ... DS13: =IF(DS$12=1,-$B$3,0)+IF(AND(DS$12>$B$6,DS$12<=$B$6+$B$7),$B$4/12,0)
A14: Cumulative | D14: =D13 | E14: =D14+E13 | F14: =E14+F13 | G14: =F14+G13 | H14: =G14+H13 | I14: =H14+I13 | J14: =I14+J13 | K14: =J14+K13 | L14: =K14+L13 | ... DS14: =DR14+DS13

Sheet Sensitivity
A1: SENSITIVITY | computed off the same mass-balance engine as MB Base / MB Sort
B3: Values are static (generated with the model engine). Re-run build_wb.py to refresh after changing Dashboard inputs.
B5: A. Capacity capture - what share of freed SAG capacity is actually filled with ore
B6: Capture | C6: ROM uplift t/h | D6: Extra oz/a | E6: Net $/a | F6: NPV $
B7: 0% | C7: 0 | D7: -566.7793 | E7: -1964635 | F7: -13861667
B8: 10% | C8: 0.72015334 | D8: -240.24489 | E8: -1010560.4 | F8: -9118735.7
B9: 21% | C9: 1.512322 | D9: 118.94295 | E9: 38921.533 | F9: -3901511.8
B10: 25% | C10: 1.8003834 | D10: 249.55671 | E10: 420551.35 | F10: -2004339.5
B11: 50% | C11: 3.6007667 | D11: 1065.8927 | E11: 2805737.7 | F11: 9852987.5
B12: 75% | C12: 5.4011501 | D12: 1882.2287 | E12: 5190924 | F12: 21710315
B13: 100% | C13: 7.2015334 | D13: 2698.5647 | E13: 7576110.3 | F13: 33567642
B16: B. Grade of the incremental feed that fills the freed capacity
B17: Incremental feed g/t | C17: ROM uplift t/h | D17: Extra oz/a | E17: Net $/a | F17: NPV $
B18: 0.8 | C18: 7.2015334 | D18: 521.66871 | E18: -1131473.8 | F18: -9719824.5
B19: 1.2 | C19: 7.2015334 | D19: 1065.8927 | E19: 1045422.3 | F19: 1102042
B20: 1.6 | C20: 7.2015334 | D20: 1610.1167 | E20: 3222318.3 | F20: 11923908
B21: 2 | C21: 7.2015334 | D21: 2154.3407 | E21: 5399214.3 | F21: 22745775
B22: 2.4 | C22: 7.2015334 | D22: 2698.5647 | E22: 7576110.3 | F22: 33567642
B23: 3 | C23: 7.2015334 | D23: 3514.9007 | E23: 10841454 | F23: 49800441
B26: C. Measured scat grade - the single most important material property
B27: Scat grade g/t | C27: Contrast x | D27: Reject grade g/t | E27: Mass pull | F27: Net $/a | G27: NPV $
B28: 0.5 | C28: 12.692308 | D28: 0.060275169 | E28: 0.5550303 | F28: 18073950 | G28: 85754893
B29: 0.8 | C29: 7.4516129 | D29: 0.10392371 | E29: 0.48264675 | F29: 16196930 | G29: 76423781
B30: 1.2 | C30: 4.4482759 | D30: 0.17616522 | E30: 0.39696433 | F30: 13536550 | G30: 63198399
B31: 1.6 | C31: 2.8518519 | D31: 0.27551867 | E31: 0.31906443 | F31: 10672874 | G31: 48962389
B32: 2 | C32: 1.8 | D32: 0.42889734 | E32: 0.24487896 | F32: 7576110.3 | G32: 33567642
B33: 2.4 | C33: 1 | D33: 0.71578947 | E33: 0.17065868 | F33: 4210345 | G33: 16835624
B36: D. Sorter performance (ore recovery / waste rejection)
B37: Ore rec / waste rej | C37: Mass pull | D37: Reject grade g/t | E37: Extra oz/a | F37: Net $/a | G37: NPV $
B38: 99% / 50% | C38: 0.16089965 | D38: 0.12903226 | E38: 2052.6915 | F38: 6053871.2 | G38: 26000230
B39: 95% / 70% | C39: 0.24487896 | D39: 0.42889734 | E39: 2698.5647 | F39: 7576110.3 | G39: 33567642
B40: 90% / 90% | C40: 0.33393502 | D40: 0.63567568 | E40: 3279.651 | F40: 8781570.7 | G40: 39560271
B41: 85% / 95% | C41: 0.3832737 | D41: 0.83173862 | E41: 3344.2946 | F41: 8411321.3 | G41: 37719673
B44: E. SLC dilution - drives the back-solved heterogeneity contrast
B45: Dilution | C45: Contrast x | D45: Mass pull | E45: Reject grade g/t | F45: Net $/a | G45: NPV $
B46: 10% | C46: 2.4545455 | D46: 0.18644068 | E46: 0.56503497 | F46: 5146371.3 | G46: 21488832
B47: 15% | C47: 2.0322581 | D47: 0.21640039 | E47: 0.48537439 | F47: 6394747.6 | G47: 27694807
B48: 20% | C48: 1.8 | D48: 0.24487896 | E48: 0.42889734 | F48: 7576110.3 | G48: 33567642
B49: 25% | C49: 1.6530612 | D49: 0.2728176 | E49: 0.38543184 | F49: 8733005.7 | G49: 39318843
B50: 30% | C50: 1.5517241 | D50: 0.30055866 | E50: 0.35050451 | F50: 9881143.2 | G50: 45026507
B53: F. Gold price and discount rate
B54: Gold price $/oz | C54: Net $/a | D54: NPV @8% | E54: NPV @10% | F54: NPV @15%
B55: 2500 | C55: 3528263.2 | D55: 15109547 | E55: 13444833 | F55: 10020169
B56: 3000 | C56: 4877545.6 | D56: 22453771 | E56: 20152436 | F56: 15418107
B57: 3500 | C57: 6226828 | D57: 29797996 | E57: 26860039 | F57: 20816046
B58: 4000 | C58: 7576110.3 | D58: 37142220 | E58: 33567642 | F58: 26213985
B59: 4500 | C59: 8925392.7 | D59: 44486444 | E59: 40275244 | F59: 31611923
B62: NPV breakeven on capacity capture is ~29%; cash breakeven ~21%.
